{
    "id": 911,
    "nombre": "skeledirge",
    "tipos": [
        "fire",
        "ghost"
    ],
    "stats_base": {
        "hp": 104,
        "attack": 75,
        "defense": 100,
        "special-attack": 110,
        "special-defense": 75,
        "speed": 66
    },
    "habilidades": {
        "normales": [
            "blaze"
        ],
        "oculta": "unaware"
    },
    "movimientos": [
        "tackle",
        "body-slam",
        "take-down",
        "leer",
        "bite",
        "roar",
        "sing",
        "ember",
        "flamethrower",
        "hyper-beam",
        "solar-beam",
        "fire-spin",
        "earthquake",
        "dig",
        "night-shade",
        "lick",
        "fire-blast",
        "rest",
        "substitute",
        "curse",
        "protect",
        "scary-face",
        "mud-slap",
        "outrage",
        "endure",
        "sleep-talk",
        "encore",
        "sunny-day",
        "crunch",
        "shadow-ball",
        "heat-wave",
        "will-o-wisp",
        "facade",
        "helping-hand",
        "imprison",
        "hyper-voice",
        "blast-burn",
        "overheat",
        "flare-blitz",
        "seed-bomb",
        "earth-power",
        "giga-impact",
        "shadow-claw",
        "thunder-fang",
        "fire-fang",
        "zen-headbutt",
        "flame-charge",
        "round",
        "hex",
        "incinerate",
        "fire-pledge",
        "heat-crash",
        "snarl",
        "disarming-voice",
        "stomping-tantrum",
        "poltergeist",
        "scorching-sands",
        "tera-blast",
        "torch-song",
        "alluring-voice",
        "temper-flare"
    ],
    "peso": 3265,
    "altura": 16
}