{
    "id": 20,
    "nombre_en": "bind",
    "nombre_es": "Atadura",
    "tipo": "normal",
    "categoria": "physical",
    "potencia": 15,
    "precision": 85,
    "pp": 20,
    "prioridad": 0,
    "generacion": "generation-i",
    "efecto": null,
    "pokemon_que_lo_aprenden": [
        "bulbasaur",
        "ivysaur",
        "venusaur",
        "ekans",
        "arbok",
        "bellsprout",
        "weepinbell",
        "victreebel",
        "tentacool",
        "tentacruel",
        "onix",
        "lickitung",
        "tangela",
        "pinsir",
        "gyarados",
        "omanyte",
        "omastar",
        "dratini",
        "dragonair",
        "dragonite",
        "mew",
        "dunsparce",
        "steelix",
        "shuckle",
        "octillery",
        "seviper",
        "lileep",
        "cradily",
        "milotic",
        "kecleon",
        "dusclops",
        "chimecho",
        "huntail",
        "gorebyss",
        "rayquaza",
        "deoxys-normal",
        "drifloon",
        "drifblim",
        "chingling",
        "carnivine",
        "lickilicky",
        "tangrowth",
        "dusknoir",
        "snivy",
        "servine",
        "serperior",
        "throh",
        "frillish",
        "jellicent",
        "klink",
        "klang",
        "klinklang",
        "eelektrik",
        "eelektross",
        "cryogonal",
        "heatmor",
        "inkay",
        "malamar",
        "zygarde-50",
        "incineroar",
        "stufful",
        "bewear",
        "comfey",
        "nihilego",
        "xurkitree",
        "stakataka",
        "sobble",
        "drizzile",
        "inteleon",
        "clobbopus",
        "grapploct",
        "zarude",
        "deoxys-attack",
        "deoxys-defense",
        "deoxys-speed",
        "venusaur-mega",
        "pinsir-mega",
        "gyarados-mega",
        "steelix-mega",
        "rayquaza-mega",
        "zygarde-10-power-construct",
        "zygarde-50-power-construct",
        "zygarde-complete",
        "stunfisk-galar",
        "zygarde-10",
        "zarude-dada"
    ]
}