{
    "id": 195,
    "nombre_en": "perish-song",
    "nombre_es": "Canto Mortal",
    "tipo": "normal",
    "categoria": "status",
    "potencia": null,
    "precision": null,
    "pp": 5,
    "prioridad": 0,
    "generacion": "generation-ii",
    "efecto": null,
    "pokemon_que_lo_aprenden": [
        "seel",
        "dewgong",
        "gastly",
        "gengar",
        "cubone",
        "jynx",
        "lapras",
        "igglybuff",
        "marill",
        "politoed",
        "murkrow",
        "misdreavus",
        "smoochum",
        "celebi",
        "azurill",
        "swablu",
        "altaria",
        "chimecho",
        "absol",
        "kricketune",
        "mismagius",
        "arceus",
        "meloetta-aria",
        "popplio",
        "brionne",
        "primarina",
        "cursola",
        "scream-tail",
        "flutter-mane",
        "meloetta-pirouette",
        "absol-mega",
        "altaria-mega"
    ]
}