{
    "id": 181,
    "nombre_en": "powder-snow",
    "nombre_es": "Nieve Polvo",
    "tipo": "ice",
    "categoria": "special",
    "potencia": 40,
    "precision": 100,
    "pp": 25,
    "prioridad": 0,
    "generacion": "generation-ii",
    "efecto": null,
    "pokemon_que_lo_aprenden": [
        "jynx",
        "articuno",
        "swinub",
        "piloswine",
        "smoochum",
        "castform",
        "snorunt",
        "glalie",
        "spheal",
        "sealeo",
        "walrein",
        "snover",
        "abomasnow",
        "glaceon",
        "mamoswine",
        "froslass",
        "vanillite",
        "cubchoo",
        "beartic",
        "amaura",
        "aurorus",
        "bergmite",
        "avalugg",
        "snom",
        "frosmoth",
        "eiscue-ice",
        "arctozolt",
        "arctovish",
        "cetoddle",
        "cetitan",
        "iron-bundle",
        "chien-pao",
        "castform-sunny",
        "castform-rainy",
        "castform-snowy",
        "abomasnow-mega",
        "glalie-mega",
        "sandshrew-alola",
        "sandslash-alola",
        "vulpix-alola",
        "ninetales-alola",
        "darumaka-galar",
        "darmanitan-galar-standard",
        "darmanitan-galar-zen",
        "eiscue-noice",
        "avalugg-hisui"
    ]
}