{
    "id": 681,
    "nombre_en": "power-trip",
    "nombre_es": "Chulería",
    "tipo": "dark",
    "categoria": "physical",
    "potencia": 20,
    "precision": 100,
    "pp": 10,
    "prioridad": 0,
    "generacion": "generation-vii",
    "efecto": null,
    "pokemon_que_lo_aprenden": [
        "mankey",
        "cacnea",
        "cacturne",
        "zangoose",
        "piplup",
        "prinplup",
        "empoleon",
        "sandile",
        "krokorok",
        "krookodile",
        "pancham",
        "litten",
        "torracat",
        "incineroar",
        "rookidee",
        "corvisquire",
        "corviknight",
        "morpeko-full-belly",
        "bombirdier",
        "morpeko-hangry"
    ]
}